cloudlink/__init__.py
cloudlink/async_iterables.py
cloudlink/client/__init__.py
cloudlink/client/protocol.py
cloudlink/client/schema.py
cloudlink/server/__init__.py
cloudlink/server/modules/__init__.py
cloudlink/server/modules/clients_manager.py
cloudlink/server/modules/rooms_manager.py
cloudlink/server/protocols/__init__.py
cloudlink/server/protocols/clpv4/__init__.py
cloudlink/server/protocols/clpv4/clpv4.py
cloudlink/server/protocols/clpv4/schema.py
cloudlink/server/protocols/scratch/__init__.py
cloudlink/server/protocols/scratch/schema.py
cloudlink/server/protocols/scratch/scratch.py
cloudlink-0.2.0.1.dist-info/LICENSE
cloudlink-0.2.0.1.dist-info/METADATA
cloudlink-0.2.0.1.dist-info/WHEEL
cloudlink-0.2.0.1.dist-info/top_level.txt
cloudlink-0.2.0.1.dist-info/RECORD
