Metadata-Version: 2.1
Name: cloudlink
Version: 0.2.0.1
Summary: A powerful WebSocket extension for Scratch.
Author-email: MikeDev101 <mike@meower.org>
License: MIT License
Project-URL: Source Code, https://github.com/MikeDev101/cloudlink
Classifier: Programming Language :: Python :: 3.11
Classifier: Operating System :: OS Independent
Requires-Python: >=3.11
License-File: LICENSE
Requires-Dist: snowflake-id >=0.0.2
Requires-Dist: cerberus >=1.3.4
Requires-Dist: websockets >=10.4
Requires-Dist: ujson >=5.7.0
